vsts/__init__.py
vsts/cli/__init__.py
vsts/cli/build/__init__.py
vsts/cli/build/common/__init__.py
vsts/cli/build/common/build.py
vsts/cli/build/common/build_definition.py
vsts/cli/build/common/task.py
vsts_cli_build_common-0.1.4.dist-info/LICENSE.txt
vsts_cli_build_common-0.1.4.dist-info/METADATA
vsts_cli_build_common-0.1.4.dist-info/WHEEL
vsts_cli_build_common-0.1.4.dist-info/top_level.txt
vsts_cli_build_common-0.1.4.dist-info/RECORD
